{
    "compatibilities": [
        "EC2",
        "MANAGED_INSTANCES",
        "FARGATE"
    ],
    "containerDefinitions": [
        {
            "cpu": 0,
            "environment": [],
            "environmentFiles": [],
            "essential": true,
            "image": "648721530572.dkr.ecr.ap-northeast-2.amazonaws.com/heylocal:lastest",
            "logConfiguration": {
                "logDriver": "awslogs",
                "options": {
                    "awslogs-group": "/ecs/heylocal-task",
                    "awslogs-create-group": "true",
                    "awslogs-region": "ap-northeast-2",
                    "awslogs-stream-prefix": "ecs"
                },
                "secretOptions": []
            },
            "mountPoints": [],
            "name": "heylocal-container",
            "portMappings": [
                {
                    "appProtocol": "http",
                    "containerPort": 8080,
                    "hostPort": 8080,
                    "name": "heylocal-container-80-tcp",
                    "protocol": "tcp"
                }
            ],
            "systemControls": [],
            "ulimits": [],
            "volumesFrom": []
        }
    ],
    "cpu": "1024",
    "enableFaultInjection": false,
    "executionRoleArn": "arn:aws:iam::648721530572:role/ecsTaskExecutionRole",
    "family": "heylocal-task",
    "memory": "3072",
    "networkMode": "awsvpc",
    "placementConstraints": [],
    "registeredAt": "2025-11-06T11:19:09.569Z",
    "registeredBy": "arn:aws:iam::648721530572:user/heylocalUser",
    "requiresAttributes": [
        {
            "name": "com.amazonaws.ecs.capability.logging-driver.awslogs"
        },
        {
            "name": "ecs.capability.execution-role-awslogs"
        },
        {
            "name": "com.amazonaws.ecs.capability.ecr-auth"
        },
        {
            "name": "com.amazonaws.ecs.capability.docker-remote-api.1.19"
        },
        {
            "name": "com.amazonaws.ecs.capability.docker-remote-api.1.21"
        },
        {
            "name": "ecs.capability.execution-role-ecr-pull"
        },
        {
            "name": "com.amazonaws.ecs.capability.docker-remote-api.1.18"
        },
        {
            "name": "ecs.capability.task-eni"
        },
        {
            "name": "com.amazonaws.ecs.capability.docker-remote-api.1.29"
        }
    ],
    "requiresCompatibilities": [
        "FARGATE"
    ],
    "revision": 1,
    "runtimePlatform": {
        "cpuArchitecture": "X86_64",
        "operatingSystemFamily": "LINUX"
    },
    "status": "ACTIVE",
    "taskDefinitionArn": "arn:aws:ecs:ap-northeast-2:648721530572:task-definition/heylocal-task:1",
    "volumes": [],
    "tags": []
}